UART/uart_rx.v
`timescale 1ns / 1ps

module uart_rx #(
    parameter integer CLK_FREQ   = 50_000_000,
    parameter integer BAUD_RATE  = 115200,
    parameter integer CLKS_PER_BIT = CLK_FREQ / BAUD_RATE
)(
    input  wire       clk,
    input  wire       rst_n,
    input  wire       rx,
    output reg        rx_valid,
    output reg [7:0]  rx_data
);

    localparam [1:0] S_IDLE  = 2'd0;
    localparam [1:0] S_START = 2'd1;
    localparam [1:0] S_DATA  = 2'd2;
    localparam [1:0] S_STOP  = 2'd3;

    reg [1:0]  state;
    reg [31:0] clk_count;
    reg [2:0]  bit_index;
    reg [7:0]  data_reg;

    reg rx_ff1, rx_ff2;

    always @(posedge clk or negedge rst_n) begin
        if (!rst_n) begin
            rx_ff1 <= 1'b1;
            rx_ff2 <= 1'b1;
        end else begin
            rx_ff1 <= rx;
            rx_ff2 <= rx_ff1;
        end
    end

    always @(posedge clk or negedge rst_n) begin
        if (!rst_n) begin
            state     <= S_IDLE;
            clk_count <= 0;
            bit_index <= 0;
            data_reg  <= 8'h00;
            rx_data   <= 8'h00;
            rx_valid  <= 1'b0;
        end else begin
            rx_valid <= 1'b0;

            case (state)
                S_IDLE: begin
                    clk_count <= 0;
                    bit_index <= 0;
                    if (rx_ff2 == 1'b0)
                        state <= S_START;
                end

                S_START: begin
                    if (clk_count < (CLKS_PER_BIT - 1) / 2) begin
                        clk_count <= clk_count + 1;
                    end else begin
                        clk_count <= 0;
                        if (rx_ff2 == 1'b0)
                            state <= S_DATA;
                        else
                            state <= S_IDLE;
                    end
                end

                S_DATA: begin
                    if (clk_count < CLKS_PER_BIT - 1) begin
                        clk_count <= clk_count + 1;
                    end else begin
                        clk_count <= 0;
                        data_reg[bit_index] <= rx_ff2;
                        if (bit_index < 3'd7) begin
                            bit_index <= bit_index + 1;
                        end else begin
                            bit_index <= 0;
                            state <= S_STOP;
                        end
                    end
                end

                S_STOP: begin
                    if (clk_count < CLKS_PER_BIT - 1) begin
                        clk_count <= clk_count + 1;
                    end else begin
                        clk_count <= 0;
                        if (rx_ff2 == 1'b1) begin
                            rx_data  <= data_reg;
                            rx_valid <= 1'b1;
                        end
                        state <= S_IDLE;
                    end
                end

                default: begin
                    state <= S_IDLE;
                end
            endcase
        end
    end

endmodule

UART/uart_tx.v
`timescale 1ns / 1ps

module uart_tx #(
    parameter integer CLK_FREQ   = 50_000_000,
    parameter integer BAUD_RATE  = 115200,
    parameter integer CLKS_PER_BIT = CLK_FREQ / BAUD_RATE
)(
    input  wire       clk,
    input  wire       rst_n,
    input  wire       tx_start,
    input  wire [7:0] tx_data,
    output reg        tx_done,
    output reg        tx
);

    localparam [1:0] S_IDLE  = 2'd0;
    localparam [1:0] S_START = 2'd1;
    localparam [1:0] S_DATA  = 2'd2;
    localparam [1:0] S_STOP  = 2'd3;

    reg [1:0]  state;
    reg [31:0] clk_count;
    reg [2:0]  bit_index;
    reg [7:0]  data_reg;

    always @(posedge clk or negedge rst_n) begin
        if (!rst_n) begin
            state     <= S_IDLE;
            clk_count <= 0;
            bit_index <= 0;
            data_reg  <= 8'h00;
            tx        <= 1'b1;
            tx_done   <= 1'b0;
        end else begin
            tx_done <= 1'b0;

            case (state)
                S_IDLE: begin
                    tx        <= 1'b1;
                    clk_count <= 0;
                    bit_index <= 0;
                    if (tx_start) begin
                        data_reg <= tx_data;
                        state    <= S_START;
                    end
                end

                S_START: begin
                    tx <= 1'b0;
                    if (clk_count < CLKS_PER_BIT - 1) begin
                        clk_count <= clk_count + 1;
                    end else begin
                        clk_count <= 0;
                        state     <= S_DATA;
                    end
                end

                S_DATA: begin
                    tx <= data_reg[bit_index];
                    if (clk_count < CLKS_PER_BIT - 1) begin
                        clk_count <= clk_count + 1;
                    end else begin
                        clk_count <= 0;
                        if (bit_index < 3'd7) begin
                            bit_index <= bit_index + 1;
                        end else begin
                            bit_index <= 0;
                            state     <= S_STOP;
                        end
                    end
                end

                S_STOP: begin
                    tx <= 1'b1;
                    if (clk_count < CLKS_PER_BIT - 1) begin
                        clk_count <= clk_count + 1;
                    end else begin
                        clk_count <= 0;
                        tx_done   <= 1'b1;
                        state     <= S_IDLE;
                    end
                end

                default: begin
                    state <= S_IDLE;
                end
            endcase
        end
    end

endmodule

UART/uart_tb.v
`timescale 1ns / 1ps

module uart_tb;

    parameter CLK_PERIOD = 20;

    reg        clk;
    reg        rst_n;
    reg        tx_start;
    reg [7:0]  tx_data;
    wire       tx_done;
    wire       tx_line;
    wire       rx_valid;
    wire [7:0] rx_data;

    uart_tx #(
        .CLK_FREQ(50_000_000),
        .BAUD_RATE(5_000_000)
    ) u_tx (
        .clk(clk),
        .rst_n(rst_n),
        .tx_start(tx_start),
        .tx_data(tx_data),
        .tx_done(tx_done),
        .tx(tx_line)
    );

    uart_rx #(
        .CLK_FREQ(50_000_000),
        .BAUD_RATE(5_000_000)
    ) u_rx (
        .clk(clk),
        .rst_n(rst_n),
        .rx(tx_line),
        .rx_valid(rx_valid),
        .rx_data(rx_data)
    );

    initial begin
        clk = 1'b0;
        forever #(CLK_PERIOD/2) clk = ~clk;
    end

    initial begin
        rst_n    = 1'b0;
        tx_start = 1'b0;
        tx_data  = 8'h00;

        #100;
        rst_n = 1'b1;

        send_byte(8'h41);
        send_byte(8'h5A);
        send_byte(8'hA5);

        #5000;
        $finish;
    end

    task send_byte(input [7:0] data);
    begin
        @(posedge clk);
        tx_data  <= data;
        tx_start <= 1'b1;
        @(posedge clk);
        tx_start <= 1'b0;

        @(posedge rx_valid);
        if (rx_data !== data)
            $error("UART loopback failed: expect=%h, recv=%h", data, rx_data);
    end
    endtask

    initial begin
        $dumpfile("uart_tb.vcd");
        $dumpvars(0, uart_tb);
    end

endmodule

UART/uart_tb.vcd
$date
	Tue Apr 21 16:11:06 2026
$end
$version
	ModelSim Version 10.1d
$end
$timescale
	1ps
$end
$scope module uart_tb $end
$var parameter 32 ! CLK_PERIOD $end
$var reg 1 " clk $end
$var reg 1 # rst_n $end
$var reg 1 $ tx_start $end
$var reg 8 % tx_data [7:0] $end
$var wire 1 & tx_done $end
$var wire 1 ' tx_line $end
$var wire 1 ( rx_valid $end
$var wire 1 ) rx_data [7] $end
$var wire 1 * rx_data [6] $end
$var wire 1 + rx_data [5] $end
$var wire 1 , rx_data [4] $end
$var wire 1 - rx_data [3] $end
$var wire 1 . rx_data [2] $end
$var wire 1 / rx_data [1] $end
$var wire 1 0 rx_data [0] $end
$scope task send_byte $end
$var reg 8 1 data [7:0] $end
$upscope $end
$scope module u_tx $end
$var parameter 32 2 CLK_FREQ $end
$var parameter 32 3 BAUD_RATE $end
$var parameter 32 4 CLKS_PER_BIT $end
$var parameter 2 5 S_IDLE $end
$var parameter 2 6 S_START $end
$var parameter 2 7 S_DATA $end
$var parameter 2 8 S_STOP $end
$var wire 1 9 clk $end
$var wire 1 : rst_n $end
$var wire 1 ; tx_start $end
$var wire 1 < tx_data [7] $end
$var wire 1 = tx_data [6] $end
$var wire 1 > tx_data [5] $end
$var wire 1 ? tx_data [4] $end
$var wire 1 @ tx_data [3] $end
$var wire 1 A tx_data [2] $end
$var wire 1 B tx_data [1] $end
$var wire 1 C tx_data [0] $end
$var reg 1 D tx_done $end
$var reg 1 E tx $end
$var reg 2 F state [1:0] $end
$var reg 32 G clk_count [31:0] $end
$var reg 3 H bit_index [2:0] $end
$var reg 8 I data_reg [7:0] $end
$upscope $end
$scope module u_rx $end
$var parameter 32 J CLK_FREQ $end
$var parameter 32 K BAUD_RATE $end
$var parameter 32 L CLKS_PER_BIT $end
$var parameter 2 M S_IDLE $end
$var parameter 2 N S_START $end
$var parameter 2 O S_DATA $end
$var parameter 2 P S_STOP $end
$var wire 1 Q clk $end
$var wire 1 R rst_n $end
$var wire 1 ' rx $end
$var reg 1 S rx_valid $end
$var reg 8 T rx_data [7:0] $end
$var reg 2 U state [1:0] $end
$var reg 32 V clk_count [31:0] $end
$var reg 3 W bit_index [2:0] $end
$var reg 8 X data_reg [7:0] $end
$var reg 1 Y rx_ff1 $end
$var reg 1 Z rx_ff2 $end
$upscope $end
$upscope $end
$enddefinitions $end
#0
$dumpvars
0"
0#
0$
b0 %
0D
1E
b0 F
b0 G
b0 H
b0 I
0S
b0 T
b0 U
b0 V
b0 W
b0 X
1Y
1Z
bx 1
b10100 !
b10111110101111000010000000 2
b10011000100101101000000 3
b1010 4
b0 5
b1 6
b10 7
b11 8
b10111110101111000010000000 J
b10011000100101101000000 K
b1010 L
b0 M
b1 N
b10 O
b11 P
0&
1'
0(
00
0/
0.
0-
0,
0+
0*
0)
0R
0Q
0C
0B
0A
0@
0?
0>
0=
0<
0;
0:
09
$end
#10000
1"
19
1Q
#20000
0"
09
0Q
#30000
1"
19
1Q
#40000
0"
09
0Q
#50000
1"
19
1Q
#60000
0"
09
0Q
#70000
1"
19
1Q
#80000
0"
09
0Q
#90000
1"
19
1Q
#100000
1#
b1000001 1
0"
1:
1R
09
0Q
#110000
1"
19
1Q
b1000001 %
1$
1C
1=
1;
#120000
0"
09
0Q
#130000
1"
19
1Q
b1000001 I
b1 F
0$
0;
#140000
0"
09
0Q
#150000
1"
19
1Q
0E
b1 G
0'
#160000
0"
09
0Q
#170000
1"
19
1Q
0Y
b10 G
#180000
0"
09
0Q
#190000
1"
19
1Q
0Z
b11 G
#200000
0"
09
0Q
#210000
1"
19
1Q
b1 U
b100 G
#220000
0"
09
0Q
#230000
1"
19
1Q
b1 V
b101 G
#240000
0"
09
0Q
#250000
1"
19
1Q
b10 V
b110 G
#260000
0"
09
0Q
#270000
1"
19
1Q
b11 V
b111 G
#280000
0"
09
0Q
#290000
1"
19
1Q
b100 V
b1000 G
#300000
0"
09
0Q
#310000
1"
19
1Q
b0 V
b10 U
b1001 G
#320000
0"
09
0Q
#330000
1"
19
1Q
b1 V
b0 G
b10 F
#340000
0"
09
0Q
#350000
1"
19
1Q
b10 V
1E
b1 G
1'
#360000
0"
09
0Q
#370000
1"
19
1Q
1Y
b11 V
b10 G
#380000
0"
09
0Q
#390000
1"
19
1Q
1Z
b100 V
b11 G
#400000
0"
09
0Q
#410000
1"
19
1Q
b101 V
b100 G
#420000
0"
09
0Q
#430000
1"
19
1Q
b110 V
b101 G
#440000
0"
09
0Q
#450000
1"
19
1Q
b111 V
b110 G
#460000
0"
09
0Q
#470000
1"
19
1Q
b1000 V
b111 G
#480000
0"
09
0Q
#490000
1"
19
1Q
b1001 V
b1000 G
#500000
0"
09
0Q
#510000
1"
19
1Q
b0 V
b1 X
b1 W
b1001 G
#520000
0"
09
0Q
#530000
1"
19
1Q
b1 V
b0 G
b1 H
#540000
0"
09
0Q
#550000
1"
19
1Q
b10 V
0E
b1 G
0'
#560000
0"
09
0Q
#570000
1"
19
1Q
0Y
b11 V
b10 G
#580000
0"
09
0Q
#590000
1"
19
1Q
0Z
b100 V
b11 G
#600000
0"
09
0Q
#610000
1"
19
1Q
b101 V
b100 G
#620000
0"
09
0Q
#630000
1"
19
1Q
b110 V
b101 G
#640000
0"
09
0Q
#650000
1"
19
1Q
b111 V
b110 G
#660000
0"
09
0Q
#670000
1"
19
1Q
b1000 V
b111 G
#680000
0"
09
0Q
#690000
1"
19
1Q
b1001 V
b1000 G
#700000
0"
09
0Q
#710000
1"
19
1Q
b0 V
b10 W
b1001 G
#720000
0"
09
0Q
#730000
1"
19
1Q
b1 V
b0 G
b10 H
#740000
0"
09
0Q
#750000
1"
19
1Q
b10 V
b1 G
#760000
0"
09
0Q
#770000
1"
19
1Q
b11 V
b10 G
#780000
0"
09
0Q
#790000
1"
19
1Q
b100 V
b11 G
#800000
0"
09
0Q
#810000
1"
19
1Q
b101 V
b100 G
#820000
0"
09
0Q
#830000
1"
19
1Q
b110 V
b101 G
#840000
0"
09
0Q
#850000
1"
19
1Q
b111 V
b110 G
#860000
0"
09
0Q
#870000
1"
19
1Q
b1000 V
b111 G
#880000
0"
09
0Q
#890000
1"
19
1Q
b1001 V
b1000 G
#900000
0"
09
0Q
#910000
1"
19
1Q
b0 V
b11 W
b1001 G
#920000
0"
09
0Q
#930000
1"
19
1Q
b1 V
b0 G
b11 H
#940000
0"
09
0Q
#950000
1"
19
1Q
b10 V
b1 G
#960000
0"
09
0Q
#970000
1"
19
1Q
b11 V
b10 G
#980000
0"
09
0Q
#990000
1"
19
1Q
b100 V
b11 G
#1000000
0"
09
0Q
#1010000
1"
19
1Q
b101 V
b100 G
#1020000
0"
09
0Q
#1030000
1"
19
1Q
b110 V
b101 G
#1040000
0"
09
0Q
#1050000
1"
19
1Q
b111 V
b110 G
#1060000
0"
09
0Q
#1070000
1"
19
1Q
b1000 V
b111 G
#1080000
0"
09
0Q
#1090000
1"
19
1Q
b1001 V
b1000 G
#1100000
0"
09
0Q
#1110000
1"
19
1Q
b0 V
b100 W
b1001 G
#1120000
0"
09
0Q
#1130000
1"
19
1Q
b1 V
b0 G
b100 H
#1140000
0"
09
0Q
#1150000
1"
19
1Q
b10 V
b1 G
#1160000
0"
09
0Q
#1170000
1"
19
1Q
b11 V
b10 G
#1180000
0"
09
0Q
#1190000
1"
19
1Q
b100 V
b11 G
#1200000
0"
09
0Q
#1210000
1"
19
1Q
b101 V
b100 G
#1220000
0"
09
0Q
#1230000
1"
19
1Q
b110 V
b101 G
#1240000
0"
09
0Q
#1250000
1"
19
1Q
b111 V
b110 G
#1260000
0"
09
0Q
#1270000
1"
19
1Q
b1000 V
b111 G
#1280000
0"
09
0Q
#1290000
1"
19
1Q
b1001 V
b1000 G
#1300000
0"
09
0Q
#1310000
1"
19
1Q
b0 V
b101 W
b1001 G
#1320000
0"
09
0Q
#1330000
1"
19
1Q
b1 V
b0 G
b101 H
#1340000
0"
09
0Q
#1350000
1"
19
1Q
b10 V
b1 G
#1360000
0"
09
0Q
#1370000
1"
19
1Q
b11 V
b10 G
#1380000
0"
09
0Q
#1390000
1"
19
1Q
b100 V
b11 G
#1400000
0"
09
0Q
#1410000
1"
19
1Q
b101 V
b100 G
#1420000
0"
09
0Q
#1430000
1"
19
1Q
b110 V
b101 G
#1440000
0"
09
0Q
#1450000
1"
19
1Q
b111 V
b110 G
#1460000
0"
09
0Q
#1470000
1"
19
1Q
b1000 V
b111 G
#1480000
0"
09
0Q
#1490000
1"
19
1Q
b1001 V
b1000 G
#1500000
0"
09
0Q
#1510000
1"
19
1Q
b0 V
b110 W
b1001 G
#1520000
0"
09
0Q
#1530000
1"
19
1Q
b1 V
b0 G
b110 H
#1540000
0"
09
0Q
#1550000
1"
19
1Q
b10 V
1E
b1 G
1'
#1560000
0"
09
0Q
#1570000
1"
19
1Q
1Y
b11 V
b10 G
#1580000
0"
09
0Q
#1590000
1"
19
1Q
1Z
b100 V
b11 G
#1600000
0"
09
0Q
#1610000
1"
19
1Q
b101 V
b100 G
#1620000
0"
09
0Q
#1630000
1"
19
1Q
b110 V
b101 G
#1640000
0"
09
0Q
#1650000
1"
19
1Q
b111 V
b110 G
#1660000
0"
09
0Q
#1670000
1"
19
1Q
b1000 V
b111 G
#1680000
0"
09
0Q
#1690000
1"
19
1Q
b1001 V
b1000 G
#1700000
0"
09
0Q
#1710000
1"
19
1Q
b0 V
b1000001 X
b111 W
b1001 G
#1720000
0"
09
0Q
#1730000
1"
19
1Q
b1 V
b0 G
b111 H
#1740000
0"
09
0Q
#1750000
1"
19
1Q
b10 V
0E
b1 G
0'
#1760000
0"
09
0Q
#1770000
1"
19
1Q
0Y
b11 V
b10 G
#1780000
0"
09
0Q
#1790000
1"
19
1Q
0Z
b100 V
b11 G
#1800000
0"
09
0Q
#1810000
1"
19
1Q
b101 V
b100 G
#1820000
0"
09
0Q
#1830000
1"
19
1Q
b110 V
b101 G
#1840000
0"
09
0Q
#1850000
1"
19
1Q
b111 V
b110 G
#1860000
0"
09
0Q
#1870000
1"
19
1Q
b1000 V
b111 G
#1880000
0"
09
0Q
#1890000
1"
19
1Q
b1001 V
b1000 G
#1900000
0"
09
0Q
#1910000
1"
19
1Q
b0 V
b0 W
b11 U
b1001 G
#1920000
0"
09
0Q
#1930000
1"
19
1Q
b1 V
b0 G
b0 H
b11 F
#1940000
0"
09
0Q
#1950000
1"
19
1Q
b10 V
1E
b1 G
1'
#1960000
0"
09
0Q
#1970000
1"
19
1Q
1Y
b11 V
b10 G
#1980000
0"
09
0Q
#1990000
1"
19
1Q
1Z
b100 V
b11 G
#2000000
0"
09
0Q
#2010000
1"
19
1Q
b101 V
b100 G
#2020000
0"
09
0Q
#2030000
1"
19
1Q
b110 V
b101 G
#2040000
0"
09
0Q
#2050000
1"
19
1Q
b111 V
b110 G
#2060000
0"
09
0Q
#2070000
1"
19
1Q
b1000 V
b111 G
#2080000
0"
09
0Q
#2090000
1"
19
1Q
b1001 V
b1000 G
#2100000
0"
09
0Q
#2110000
1"
19
1Q
b0 V
b1000001 T
1S
b0 U
b1001 G
10
1*
1(
b1011010 1
#2120000
0"
09
0Q
#2130000
1"
19
1Q
0S
b0 G
1D
b0 F
b1011010 %
1$
1&
0C
1B
1@
1?
1;
0(
#2140000
0"
09
0Q
#2150000
1"
19
1Q
0D
b1011010 I
b1 F
0$
0&
0;
#2160000
0"
09
0Q
#2170000
1"
19
1Q
0E
b1 G
0'
#2180000
0"
09
0Q
#2190000
1"
19
1Q
0Y
b10 G
#2200000
0"
09
0Q
#2210000
1"
19
1Q
0Z
b11 G
#2220000
0"
09
0Q
#2230000
1"
19
1Q
b1 U
b100 G
#2240000
0"
09
0Q
#2250000
1"
19
1Q
b1 V
b101 G
#2260000
0"
09
0Q
#2270000
1"
19
1Q
b10 V
b110 G
#2280000
0"
09
0Q
#2290000
1"
19
1Q
b11 V
b111 G
#2300000
0"
09
0Q
#2310000
1"
19
1Q
b100 V
b1000 G
#2320000
0"
09
0Q
#2330000
1"
19
1Q
b0 V
b10 U
b1001 G
#2340000
0"
09
0Q
#2350000
1"
19
1Q
b1 V
b0 G
b10 F
#2360000
0"
09
0Q
#2370000
1"
19
1Q
b10 V
b1 G
#2380000
0"
09
0Q
#2390000
1"
19
1Q
b11 V
b10 G
#2400000
0"
09
0Q
#2410000
1"
19
1Q
b100 V
b11 G
#2420000
0"
09
0Q
#2430000
1"
19
1Q
b101 V
b100 G
#2440000
0"
09
0Q
#2450000
1"
19
1Q
b110 V
b101 G
#2460000
0"
09
0Q
#2470000
1"
19
1Q
b111 V
b110 G
#2480000
0"
09
0Q
#2490000
1"
19
1Q
b1000 V
b111 G
#2500000
0"
09
0Q
#2510000
1"
19
1Q
b1001 V
b1000 G
#2520000
0"
09
0Q
#2530000
1"
19
1Q
b0 V
b1000000 X
b1 W
b1001 G
#2540000
0"
09
0Q
#2550000
1"
19
1Q
b1 V
b0 G
b1 H
#2560000
0"
09
0Q
#2570000
1"
19
1Q
b10 V
1E
b1 G
1'
#2580000
0"
09
0Q
#2590000
1"
19
1Q
1Y
b11 V
b10 G
#2600000
0"
09
0Q
#2610000
1"
19
1Q
1Z
b100 V
b11 G
#2620000
0"
09
0Q
#2630000
1"
19
1Q
b101 V
b100 G
#2640000
0"
09
0Q
#2650000
1"
19
1Q
b110 V
b101 G
#2660000
0"
09
0Q
#2670000
1"
19
1Q
b111 V
b110 G
#2680000
0"
09
0Q
#2690000
1"
19
1Q
b1000 V
b111 G
#2700000
0"
09
0Q
#2710000
1"
19
1Q
b1001 V
b1000 G
#2720000
0"
09
0Q
#2730000
1"
19
1Q
b0 V
b1000010 X
b10 W
b1001 G
#2740000
0"
09
0Q
#2750000
1"
19
1Q
b1 V
b0 G
b10 H
#2760000
0"
09
0Q
#2770000
1"
19
1Q
b10 V
0E
b1 G
0'
#2780000
0"
09
0Q
#2790000
1"
19
1Q
0Y
b11 V
b10 G
#2800000
0"
09
0Q
#2810000
1"
19
1Q
0Z
b100 V
b11 G
#2820000
0"
09
0Q
#2830000
1"
19
1Q
b101 V
b100 G
#2840000
0"
09
0Q
#2850000
1"
19
1Q
b110 V
b101 G
#2860000
0"
09
0Q
#2870000
1"
19
1Q
b111 V
b110 G
#2880000
0"
09
0Q
#2890000
1"
19
1Q
b1000 V
b111 G
#2900000
0"
09
0Q
#2910000
1"
19
1Q
b1001 V
b1000 G
#2920000
0"
09
0Q
#2930000
1"
19
1Q
b0 V
b11 W
b1001 G
#2940000
0"
09
0Q
#2950000
1"
19
1Q
b1 V
b0 G
b11 H
#2960000
0"
09
0Q
#2970000
1"
19
1Q
b10 V
1E
b1 G
1'
#2980000
0"
09
0Q
#2990000
1"
19
1Q
1Y
b11 V
b10 G
#3000000
0"
09
0Q
#3010000
1"
19
1Q
1Z
b100 V
b11 G
#3020000
0"
09
0Q
#3030000
1"
19
1Q
b101 V
b100 G
#3040000
0"
09
0Q
#3050000
1"
19
1Q
b110 V
b101 G
#3060000
0"
09
0Q
#3070000
1"
19
1Q
b111 V
b110 G
#3080000
0"
09
0Q
#3090000
1"
19
1Q
b1000 V
b111 G
#3100000
0"
09
0Q
#3110000
1"
19
1Q
b1001 V
b1000 G
#3120000
0"
09
0Q
#3130000
1"
19
1Q
b0 V
b1001010 X
b100 W
b1001 G
#3140000
0"
09
0Q
#3150000
1"
19
1Q
b1 V
b0 G
b100 H
#3160000
0"
09
0Q
#3170000
1"
19
1Q
b10 V
b1 G
#3180000
0"
09
0Q
#3190000
1"
19
1Q
b11 V
b10 G
#3200000
0"
09
0Q
#3210000
1"
19
1Q
b100 V
b11 G
#3220000
0"
09
0Q
#3230000
1"
19
1Q
b101 V
b100 G
#3240000
0"
09
0Q
#3250000
1"
19
1Q
b110 V
b101 G
#3260000
0"
09
0Q
#3270000
1"
19
1Q
b111 V
b110 G
#3280000
0"
09
0Q
#3290000
1"
19
1Q
b1000 V
b111 G
#3300000
0"
09
0Q
#3310000
1"
19
1Q
b1001 V
b1000 G
#3320000
0"
09
0Q
#3330000
1"
19
1Q
b0 V
b1011010 X
b101 W
b1001 G
#3340000
0"
09
0Q
#3350000
1"
19
1Q
b1 V
b0 G
b101 H
#3360000
0"
09
0Q
#3370000
1"
19
1Q
b10 V
0E
b1 G
0'
#3380000
0"
09
0Q
#3390000
1"
19
1Q
0Y
b11 V
b10 G
#3400000
0"
09
0Q
#3410000
1"
19
1Q
0Z
b100 V
b11 G
#3420000
0"
09
0Q
#3430000
1"
19
1Q
b101 V
b100 G
#3440000
0"
09
0Q
#3450000
1"
19
1Q
b110 V
b101 G
#3460000
0"
09
0Q
#3470000
1"
19
1Q
b111 V
b110 G
#3480000
0"
09
0Q
#3490000
1"
19
1Q
b1000 V
b111 G
#3500000
0"
09
0Q
#3510000
1"
19
1Q
b1001 V
b1000 G
#3520000
0"
09
0Q
#3530000
1"
19
1Q
b0 V
b110 W
b1001 G
#3540000
0"
09
0Q
#3550000
1"
19
1Q
b1 V
b0 G
b110 H
#3560000
0"
09
0Q
#3570000
1"
19
1Q
b10 V
1E
b1 G
1'
#3580000
0"
09
0Q
#3590000
1"
19
1Q
1Y
b11 V
b10 G
#3600000
0"
09
0Q
#3610000
1"
19
1Q
1Z
b100 V
b11 G
#3620000
0"
09
0Q
#3630000
1"
19
1Q
b101 V
b100 G
#3640000
0"
09
0Q
#3650000
1"
19
1Q
b110 V
b101 G
#3660000
0"
09
0Q
#3670000
1"
19
1Q
b111 V
b110 G
#3680000
0"
09
0Q
#3690000
1"
19
1Q
b1000 V
b111 G
#3700000
0"
09
0Q
#3710000
1"
19
1Q
b1001 V
b1000 G
#3720000
0"
09
0Q
#3730000
1"
19
1Q
b0 V
b111 W
b1001 G
#3740000
0"
09
0Q
#3750000
1"
19
1Q
b1 V
b0 G
b111 H
#3760000
0"
09
0Q
#3770000
1"
19
1Q
b10 V
0E
b1 G
0'
#3780000
0"
09
0Q
#3790000
1"
19
1Q
0Y
b11 V
b10 G
#3800000
0"
09
0Q
#3810000
1"
19
1Q
0Z
b100 V
b11 G
#3820000
0"
09
0Q
#3830000
1"
19
1Q
b101 V
b100 G
#3840000
0"
09
0Q
#3850000
1"
19
1Q
b110 V
b101 G
#3860000
0"
09
0Q
#3870000
1"
19
1Q
b111 V
b110 G
#3880000
0"
09
0Q
#3890000
1"
19
1Q
b1000 V
b111 G
#3900000
0"
09
0Q
#3910000
1"
19
1Q
b1001 V
b1000 G
#3920000
0"
09
0Q
#3930000
1"
19
1Q
b0 V
b0 W
b11 U
b1001 G
#3940000
0"
09
0Q
#3950000
1"
19
1Q
b1 V
b0 G
b0 H
b11 F
#3960000
0"
09
0Q
#3970000
1"
19
1Q
b10 V
1E
b1 G
1'
#3980000
0"
09
0Q
#3990000
1"
19
1Q
1Y
b11 V
b10 G
#4000000
0"
09
0Q
#4010000
1"
19
1Q
1Z
b100 V
b11 G
#4020000
0"
09
0Q
#4030000
1"
19
1Q
b101 V
b100 G
#4040000
0"
09
0Q
#4050000
1"
19
1Q
b110 V
b101 G
#4060000
0"
09
0Q
#4070000
1"
19
1Q
b111 V
b110 G
#4080000
0"
09
0Q
#4090000
1"
19
1Q
b1000 V
b111 G
#4100000
0"
09
0Q
#4110000
1"
19
1Q
b1001 V
b1000 G
#4120000
0"
09
0Q
#4130000
1"
19
1Q
b0 V
b1011010 T
1S
b0 U
b1001 G
00
1/
1-
1,
1(
b10100101 1
#4140000
0"
09
0Q
#4150000
1"
19
1Q
0S
b0 G
1D
b0 F
b10100101 %
1$
1&
1C
0B
1A
0@
0?
1>
0=
1<
1;
0(
#4160000
0"
09
0Q
#4170000
1"
19
1Q
0D
b10100101 I
b1 F
0$
0&
0;
#4180000
0"
09
0Q
#4190000
1"
19
1Q
0E
b1 G
0'
#4200000
0"
09
0Q
#4210000
1"
19
1Q
0Y
b10 G
#4220000
0"
09
0Q
#4230000
1"
19
1Q
0Z
b11 G
#4240000
0"
09
0Q
#4250000
1"
19
1Q
b1 U
b100 G
#4260000
0"
09
0Q
#4270000
1"
19
1Q
b1 V
b101 G
#4280000
0"
09
0Q
#4290000
1"
19
1Q
b10 V
b110 G
#4300000
0"
09
0Q
#4310000
1"
19
1Q
b11 V
b111 G
#4320000
0"
09
0Q
#4330000
1"
19
1Q
b100 V
b1000 G
#4340000
0"
09
0Q
#4350000
1"
19
1Q
b0 V
b10 U
b1001 G
#4360000
0"
09
0Q
#4370000
1"
19
1Q
b1 V
b0 G
b10 F
#4380000
0"
09
0Q
#4390000
1"
19
1Q
b10 V
1E
b1 G
1'
#4400000
0"
09
0Q
#4410000
1"
19
1Q
1Y
b11 V
b10 G
#4420000
0"
09
0Q
#4430000
1"
19
1Q
1Z
b100 V
b11 G
#4440000
0"
09
0Q
#4450000
1"
19
1Q
b101 V
b100 G
#4460000
0"
09
0Q
#4470000
1"
19
1Q
b110 V
b101 G
#4480000
0"
09
0Q
#4490000
1"
19
1Q
b111 V
b110 G
#4500000
0"
09
0Q
#4510000
1"
19
1Q
b1000 V
b111 G
#4520000
0"
09
0Q
#4530000
1"
19
1Q
b1001 V
b1000 G
#4540000
0"
09
0Q
#4550000
1"
19
1Q
b0 V
b1011011 X
b1 W
b1001 G
#4560000
0"
09
0Q
#4570000
1"
19
1Q
b1 V
b0 G
b1 H
#4580000
0"
09
0Q
#4590000
1"
19
1Q
b10 V
0E
b1 G
0'
#4600000
0"
09
0Q
#4610000
1"
19
1Q
0Y
b11 V
b10 G
#4620000
0"
09
0Q
#4630000
1"
19
1Q
0Z
b100 V
b11 G
#4640000
0"
09
0Q
#4650000
1"
19
1Q
b101 V
b100 G
#4660000
0"
09
0Q
#4670000
1"
19
1Q
b110 V
b101 G
#4680000
0"
09
0Q
#4690000
1"
19
1Q
b111 V
b110 G
#4700000
0"
09
0Q
#4710000
1"
19
1Q
b1000 V
b111 G
#4720000
0"
09
0Q
#4730000
1"
19
1Q
b1001 V
b1000 G
#4740000
0"
09
0Q
#4750000
1"
19
1Q
b0 V
b1011001 X
b10 W
b1001 G
#4760000
0"
09
0Q
#4770000
1"
19
1Q
b1 V
b0 G
b10 H
#4780000
0"
09
0Q
#4790000
1"
19
1Q
b10 V
1E
b1 G
1'
#4800000
0"
09
0Q
#4810000
1"
19
1Q
1Y
b11 V
b10 G
#4820000
0"
09
0Q
#4830000
1"
19
1Q
1Z
b100 V
b11 G
#4840000
0"
09
0Q
#4850000
1"
19
1Q
b101 V
b100 G
#4860000
0"
09
0Q
#4870000
1"
19
1Q
b110 V
b101 G
#4880000
0"
09
0Q
#4890000
1"
19
1Q
b111 V
b110 G
#4900000
0"
09
0Q
#4910000
1"
19
1Q
b1000 V
b111 G
#4920000
0"
09
0Q
#4930000
1"
19
1Q
b1001 V
b1000 G
#4940000
0"
09
0Q
#4950000
1"
19
1Q
b0 V
b1011101 X
b11 W
b1001 G
#4960000
0"
09
0Q
#4970000
1"
19
1Q
b1 V
b0 G
b11 H
#4980000
0"
09
0Q
#4990000
1"
19
1Q
b10 V
0E
b1 G
0'
#5000000
0"
09
0Q
#5010000
1"
19
1Q
0Y
b11 V
b10 G
#5020000
0"
09
0Q
#5030000
1"
19
1Q
0Z
b100 V
b11 G
#5040000
0"
09
0Q
#5050000
1"
19
1Q
b101 V
b100 G
#5060000
0"
09
0Q
#5070000
1"
19
1Q
b110 V
b101 G
#5080000
0"
09
0Q
#5090000
1"
19
1Q
b111 V
b110 G
#5100000
0"
09
0Q
#5110000
1"
19
1Q
b1000 V
b111 G
#5120000
0"
09
0Q
#5130000
1"
19
1Q
b1001 V
b1000 G
#5140000
0"
09
0Q
#5150000
1"
19
1Q
b0 V
b1010101 X
b100 W
b1001 G
#5160000
0"
09
0Q
#5170000
1"
19
1Q
b1 V
b0 G
b100 H
#5180000
0"
09
0Q
#5190000
1"
19
1Q
b10 V
b1 G
#5200000
0"
09
0Q
#5210000
1"
19
1Q
b11 V
b10 G
#5220000
0"
09
0Q
