SPI/spi_slave.v
`timescale 1ns / 1ps

module spi_slave #(
    parameter [7:0] RESPONSE_DATA = 8'h3C
)(
    input  wire      rst_n,
    input  wire      sclk,
    input  wire      cs_n,
    input  wire      mosi,
    output reg       miso,
    output reg [7:0] rx_data,
    output reg       rx_done
);

    reg [7:0] tx_shift;
    reg [7:0] rx_shift;
    reg [2:0] bit_count;

    always @(negedge cs_n or negedge rst_n) begin
        if (!rst_n) begin
            tx_shift  <= 8'h00;
            rx_shift  <= 8'h00;
            bit_count <= 3'd7;
            miso      <= 1'b0;
            rx_data   <= 8'h00;
            rx_done   <= 1'b0;
        end else begin
            tx_shift  <= RESPONSE_DATA;
            rx_shift  <= 8'h00;
            bit_count <= 3'd7;
            miso      <= RESPONSE_DATA[7];
            rx_done   <= 1'b0;
        end
    end

    always @(posedge sclk or negedge rst_n) begin
        if (!rst_n) begin
            rx_shift  <= 8'h00;
            bit_count <= 3'd7;
            rx_data   <= 8'h00;
            rx_done   <= 1'b0;
        end else if (!cs_n) begin
            rx_shift[bit_count] <= mosi;
            if (bit_count == 3'd0) begin
                rx_data   <= {rx_shift[7:1], mosi};
                bit_count <= 3'd7;
                rx_done   <= 1'b1;
            end else begin
                bit_count <= bit_count - 1'b1;
                rx_done   <= 1'b0;
            end
        end else begin
            rx_done <= 1'b0;
        end
    end

    always @(negedge sclk or negedge rst_n) begin
        if (!rst_n) begin
            tx_shift <= 8'h00;
            miso     <= 1'b0;
        end else if (!cs_n) begin
            tx_shift <= {tx_shift[6:0], 1'b0};
            miso     <= tx_shift[6];
        end else begin
            miso <= 1'b0;
        end
    end

endmodule

SPI/spi_master.v
`timescale 1ns / 1ps

module spi_master #(
    parameter integer CLK_DIV = 4
)(
    input  wire       clk,
    input  wire       rst_n,
    input  wire       start,
    input  wire [7:0] tx_data,
    output reg  [7:0] rx_data,
    output reg        busy,
    output reg        done,
    output reg        sclk,
    output reg        mosi,
    input  wire       miso,
    output reg        cs_n
);

    localparam [1:0] S_IDLE     = 2'd0;
    localparam [1:0] S_TRANSFER = 2'd1;
    localparam [1:0] S_FINISH   = 2'd2;

    reg [1:0] state;
    reg [7:0] tx_shift;
    reg [7:0] rx_shift;
    reg [2:0] bit_count;
    reg [15:0] clk_div_count;

    always @(posedge clk or negedge rst_n) begin
        if (!rst_n) begin
            state         <= S_IDLE;
            tx_shift      <= 8'h00;
            rx_shift      <= 8'h00;
            bit_count     <= 3'd0;
            clk_div_count <= 16'd0;
            rx_data       <= 8'h00;
            busy          <= 1'b0;
            done          <= 1'b0;
            sclk          <= 1'b0;
            mosi          <= 1'b0;
            cs_n          <= 1'b1;
        end else begin
            done <= 1'b0;

            case (state)
                S_IDLE: begin
                    busy          <= 1'b0;
                    cs_n          <= 1'b1;
                    sclk          <= 1'b0;
                    clk_div_count <= 16'd0;
                    if (start) begin
                        busy      <= 1'b1;
                        cs_n      <= 1'b0;
                        tx_shift  <= tx_data;
                        rx_shift  <= 8'h00;
                        bit_count <= 3'd7;
                        mosi      <= tx_data[7];
                        state     <= S_TRANSFER;
                    end
                end

                S_TRANSFER: begin
                    if (clk_div_count < (CLK_DIV - 1)) begin
                        clk_div_count <= clk_div_count + 1'b1;
                    end else begin
                        clk_div_count <= 16'd0;
                        sclk <= ~sclk;

                        if (sclk == 1'b0) begin
                            rx_shift[bit_count] <= miso;
                            if (bit_count == 3'd0) begin
                                state <= S_FINISH;
                            end else begin
                                bit_count <= bit_count - 1'b1;
                            end
                        end else begin
                            mosi <= tx_shift[bit_count];
                        end
                    end
                end

                S_FINISH: begin
                    busy    <= 1'b0;
                    cs_n    <= 1'b1;
                    sclk    <= 1'b0;
                    rx_data <= rx_shift;
                    done    <= 1'b1;
                    state   <= S_IDLE;
                end

                default: begin
                    state <= S_IDLE;
                end
            endcase
        end
    end

endmodule

SPI/spi_tb.v
`timescale 1ns / 1ps

module spi_tb;

    parameter CLK_PERIOD = 20;
    parameter [7:0] MASTER_TX = 8'hA5;
    parameter [7:0] SLAVE_TX  = 8'h3C;

    reg        clk;
    reg        rst_n;
    reg        start;
    reg [7:0]  tx_data;
    wire [7:0] rx_data;
    wire       busy;
    wire       done;
    wire       sclk;
    wire       mosi;
    wire       miso;
    wire       cs_n;
    wire [7:0] slave_rx_data;
    wire       slave_rx_done;

    spi_master #(
        .CLK_DIV(4)
    ) u_master (
        .clk(clk),
        .rst_n(rst_n),
        .start(start),
        .tx_data(tx_data),
        .rx_data(rx_data),
        .busy(busy),
        .done(done),
        .sclk(sclk),
        .mosi(mosi),
        .miso(miso),
        .cs_n(cs_n)
    );

    spi_slave #(
        .RESPONSE_DATA(SLAVE_TX)
    ) u_slave (
        .rst_n(rst_n),
        .sclk(sclk),
        .cs_n(cs_n),
        .mosi(mosi),
        .miso(miso),
        .rx_data(slave_rx_data),
        .rx_done(slave_rx_done)
    );

    initial begin
        clk = 1'b0;
        forever #(CLK_PERIOD/2) clk = ~clk;
    end

    initial begin
        rst_n   = 1'b0;
        start   = 1'b0;
        tx_data = 8'h00;

        #100;
        rst_n = 1'b1;

        @(posedge clk);
        tx_data <= MASTER_TX;
        start   <= 1'b1;
        @(posedge clk);
        start   <= 1'b0;

        @(posedge done);

        if (rx_data !== SLAVE_TX) begin
            $error("Master RX mismatch: expect=%h recv=%h", SLAVE_TX, rx_data);
        end

        if (slave_rx_data !== MASTER_TX) begin
            $error("Slave RX mismatch: expect=%h recv=%h", MASTER_TX, slave_rx_data);
        end

        #200;
        $finish;
    end

    initial begin
        $dumpfile("spi_tb.vcd");
        $dumpvars(0, spi_tb);
    end

endmodule

SPI/spi_tb.vcd
$date
	Tue Apr 21 20:32:55 2026
$end
$version
	ModelSim Version 10.1d
$end
$timescale
	1ps
$end
$scope module spi_tb $end
$var parameter 32 ! CLK_PERIOD $end
$var parameter 8 " MASTER_TX $end
$var parameter 8 # SLAVE_TX $end
$var reg 1 $ clk $end
$var reg 1 % rst_n $end
$var reg 1 & start $end
$var reg 8 ' tx_data [7:0] $end
$var wire 1 ( rx_data [7] $end
$var wire 1 ) rx_data [6] $end
$var wire 1 * rx_data [5] $end
$var wire 1 + rx_data [4] $end
$var wire 1 , rx_data [3] $end
$var wire 1 - rx_data [2] $end
$var wire 1 . rx_data [1] $end
$var wire 1 / rx_data [0] $end
$var wire 1 0 busy $end
$var wire 1 1 done $end
$var wire 1 2 sclk $end
$var wire 1 3 mosi $end
$var wire 1 4 miso $end
$var wire 1 5 cs_n $end
$var wire 1 6 slave_rx_data [7] $end
$var wire 1 7 slave_rx_data [6] $end
$var wire 1 8 slave_rx_data [5] $end
$var wire 1 9 slave_rx_data [4] $end
$var wire 1 : slave_rx_data [3] $end
$var wire 1 ; slave_rx_data [2] $end
$var wire 1 < slave_rx_data [1] $end
$var wire 1 = slave_rx_data [0] $end
$var wire 1 > slave_rx_done $end
$scope module u_master $end
$var parameter 32 ? CLK_DIV $end
$var parameter 2 @ S_IDLE $end
$var parameter 2 A S_TRANSFER $end
$var parameter 2 B S_FINISH $end
$var wire 1 C clk $end
$var wire 1 D rst_n $end
$var wire 1 E start $end
$var wire 1 F tx_data [7] $end
$var wire 1 G tx_data [6] $end
$var wire 1 H tx_data [5] $end
$var wire 1 I tx_data [4] $end
$var wire 1 J tx_data [3] $end
$var wire 1 K tx_data [2] $end
$var wire 1 L tx_data [1] $end
$var wire 1 M tx_data [0] $end
$var reg 8 N rx_data [7:0] $end
$var reg 1 O busy $end
$var reg 1 P done $end
$var reg 1 Q sclk $end
$var reg 1 R mosi $end
$var wire 1 4 miso $end
$var reg 1 S cs_n $end
$var reg 2 T state [1:0] $end
$var reg 8 U tx_shift [7:0] $end
$var reg 8 V rx_shift [7:0] $end
$var reg 3 W bit_count [2:0] $end
$var reg 16 X clk_div_count [15:0] $end
$upscope $end
$scope module u_slave $end
$var parameter 8 Y RESPONSE_DATA $end
$var wire 1 Z rst_n $end
$var wire 1 2 sclk $end
$var wire 1 5 cs_n $end
$var wire 1 3 mosi $end
$var reg 1 [ miso $end
$var reg 8 \ rx_data [7:0] $end
$var reg 1 ] rx_done $end
$var reg 8 ^ tx_shift [7:0] $end
$var reg 8 _ rx_shift [7:0] $end
$var reg 3 ` bit_count [2:0] $end
$upscope $end
$upscope $end
$enddefinitions $end
#0
$dumpvars
0$
0%
0&
b0 '
b0 N
0O
0P
0Q
0R
1S
b0 T
b0 U
b0 V
b0 W
b0 X
0[
b0 \
0]
b0 ^
b0 _
b111 `
b10100 !
b10100101 "
b111100 #
b100 ?
b0 @
b1 A
b10 B
b111100 Y
0/
0.
0-
0,
0+
0*
0)
0(
00
01
02
03
04
15
0=
0<
0;
0:
09
08
07
06
0>
0Z
0M
0L
0K
0J
0I
0H
0G
0F
0E
0D
0C
$end
#10000
1$
1C
#20000
0$
0C
#30000
1$
1C
#40000
0$
0C
#50000
1$
1C
#60000
0$
0C
#70000
1$
1C
#80000
0$
0C
#90000
1$
1C
#100000
1%
0$
1D
1Z
0C
#110000
1$
1C
b10100101 '
1&
1M
1K
1H
1F
1E
#120000
0$
0C
#130000
1$
1C
1O
0S
b10100101 U
b111 W
1R
b1 T
0&
10
13
0E
05
b111100 ^
#140000
0$
0C
#150000
1$
1C
b1 X
#160000
0$
0C
#170000
1$
1C
b10 X
#180000
0$
0C
#190000
1$
1C
b11 X
#200000
0$
0C
#210000
1$
1C
b0 X
1Q
b110 W
12
b10000000 _
b110 `
#220000
0$
0C
#230000
1$
1C
b1 X
#240000
0$
0C
#250000
1$
1C
b10 X
#260000
0$
0C
#270000
1$
1C
b11 X
#280000
0$
0C
#290000
1$
1C
b0 X
0Q
0R
03
02
b1111000 ^
#300000
0$
0C
#310000
1$
1C
b1 X
#320000
0$
0C
#330000
1$
1C
b10 X
#340000
0$
0C
#350000
1$
1C
b11 X
#360000
0$
0C
#370000
1$
1C
b0 X
1Q
b101 W
12
b101 `
#380000
0$
0C
#390000
1$
1C
b1 X
#400000
0$
0C
#410000
1$
1C
b10 X
#420000
0$
0C
#430000
1$
1C
b11 X
#440000
0$
0C
#450000
1$
1C
b0 X
0Q
1R
13
02
b11110000 ^
1[
14
#460000
0$
0C
#470000
1$
1C
b1 X
#480000
0$
0C
#490000
1$
1C
b10 X
#500000
0$
0C
#510000
1$
1C
b11 X
#520000
0$
0C
#530000
1$
1C
b0 X
1Q
b100000 V
b100 W
12
b10100000 _
b100 `
#540000
0$
0C
#550000
1$
1C
b1 X
#560000
0$
0C
#570000
1$
1C
b10 X
#580000
0$
0C
#590000
1$
1C
b11 X
#600000
0$
0C
#610000
1$
1C
b0 X
0Q
0R
03
02
b11100000 ^
#620000
0$
0C
#630000
1$
1C
b1 X
#640000
0$
0C
#650000
1$
1C
b10 X
#660000
0$
0C
#670000
1$
1C
b11 X
#680000
0$
0C
#690000
1$
1C
b0 X
1Q
b110000 V
b11 W
12
b11 `
#700000
0$
0C
#710000
1$
1C
b1 X
#720000
0$
0C
#730000
1$
1C
b10 X
#740000
0$
0C
#750000
1$
1C
b11 X
#760000
0$
0C
#770000
1$
1C
b0 X
0Q
02
b11000000 ^
#780000
0$
0C
#790000
1$
1C
b1 X
#800000
0$
0C
#810000
1$
1C
b10 X
#820000
0$
0C
#830000
1$
1C
b11 X
#840000
0$
0C
#850000
1$
1C
b0 X
1Q
b111000 V
b10 W
12
b10 `
#860000
0$
0C
#870000
1$
1C
b1 X
#880000
0$
0C
#890000
1$
1C
b10 X
#900000
0$
0C
#910000
1$
1C
b11 X
#920000
0$
0C
#930000
1$
1C
b0 X
0Q
1R
13
02
b10000000 ^
#940000
0$
0C
#950000
1$
1C
b1 X
#960000
0$
0C
#970000
1$
1C
b10 X
#980000
0$
0C
#990000
1$
1C
b11 X
#1000000
0$
0C
#1010000
1$
1C
b0 X
1Q
b111100 V
b1 W
12
b10100100 _
b1 `
#1020000
0$
0C
#1030000
1$
1C
b1 X
#1040000
0$
0C
#1050000
1$
1C
b10 X
#1060000
0$
0C
#1070000
1$
1C
b11 X
#1080000
0$
0C
#1090000
1$
1C
b0 X
0Q
0R
03
02
b0 ^
0[
04
#1100000
0$
0C
#1110000
1$
1C
b1 X
#1120000
0$
0C
#1130000
1$
1C
b10 X
#1140000
0$
0C
#1150000
1$
1C
b11 X
#1160000
0$
0C
#1170000
1$
1C
b0 X
1Q
b0 W
12
b0 `
#1180000
0$
0C
#1190000
1$
1C
b1 X
#1200000
0$
0C
#1210000
1$
1C
b10 X
#1220000
0$
0C
#1230000
1$
1C
b11 X
#1240000
0$
0C
#1250000
1$
1C
b0 X
0Q
1R
13
02
#1260000
0$
0C
#1270000
1$
1C
b1 X
#1280000
0$
0C
#1290000
1$
1C
b10 X
#1300000
0$
0C
#1310000
1$
1C
b11 X
#1320000
0$
0C
#1330000
1$
1C
b0 X
1Q
b10 T
12
b10100101 _
b10100101 \
b111 `
1]
1=
1;
18
16
1>
#1340000
0$
0C
#1350000
1$
1C
0O
1S
0Q
b111100 N
1P
b0 T
00
1-
1,
1+
1*
15
02
11
#1360000
0$
0C
#1370000
1$
1C
0P
01
